{
  "products": [
    {
      "id": 1,
      "name": "Mens fleece hoodie",
      "category": "top",
      "price": 75,
      "sizes": [
        "XS",
        "S",
        "M",
        "L"
      ],
      "image": "/assets/images/top_1.png"
    },
    {
      "id": 2,
      "name": "Running Hoodie",
      "category": "top",
      "price": 75,
      "sizes": [
        "S",
        "M",
        "L"
      ],
      "image": "/assets/images/top_2.png"
    },
    {
      "id": 3,
      "name": "Training Pants",
      "category": "bottom",
      "price": 80,
      "sizes": [
        "M",
        "L",
        "XL"
      ],
      "image": "/assets/images/pants.jpg"
    },
    {
      "id": 4,
      "name": "Sport Cap",
      "category": "accessories",
      "price": 25,
      "sizes": [
        "all"
      ],
      "image": "/assets/images/cap.jpg"
    }
  ],
  "cart": []
}